LICENSE
README.md
aiometrics.py
setup.py
aiometrics.egg-info/PKG-INFO
aiometrics.egg-info/SOURCES.txt
aiometrics.egg-info/dependency_links.txt
aiometrics.egg-info/requires.txt
aiometrics.egg-info/top_level.txt