Metadata-Version: 1.0
Name: aiometrics
Version: 0.1.4
Summary: Generate metrics from AsyncIO applications
Home-page: https://github.com/dmonroy/aiometrics
Author: Darwin Monroy
Author-email: contact@darwinmonroy.com
License: MIT License
Platform: UNKNOWN
